app/__init__.py
app/main.py
app/dynamodb/__init__.py
app/dynamodb/csv_export.py
app/dynamodb/csv_import.py
app/dynamodb/move.py
app/dynamodb/truncate.py
dynamodb_csv-1.5.5.dist-info/LICENSE
dynamodb_csv-1.5.5.dist-info/METADATA
dynamodb_csv-1.5.5.dist-info/WHEEL
dynamodb_csv-1.5.5.dist-info/entry_points.txt
dynamodb_csv-1.5.5.dist-info/top_level.txt
dynamodb_csv-1.5.5.dist-info/RECORD
