Metadata-Version: 2.1
Name: dynamodb-csv
Version: 1.5.5
Summary: A utility that allows CSV import / export to DynamoDB on the command line
Home-page: https://github.com/danishi/dynamodb-csv
Author: danishi
Author-email: dns2developer@gmail.com
License: MIT
Keywords: AWS,DynamoDB,CSV
Classifier: Development Status :: 5 - Production/Stable
Classifier: Programming Language :: Python
Classifier: Programming Language :: Python :: 3
Classifier: Programming Language :: Python :: 3.9
Classifier: Programming Language :: Python :: 3.10
Classifier: Programming Language :: Python :: 3.11
Classifier: Programming Language :: Python :: 3.12
Classifier: Programming Language :: Python :: 3.13
Classifier: Topic :: Utilities
Requires-Python: >=3.9
License-File: LICENSE
Requires-Dist: boto3
Requires-Dist: configparser
Requires-Dist: tqdm
